README.txt
setup.cfg
setup.py
targetlib/__init__.py
testqqtest.egg-info/PKG-INFO
testqqtest.egg-info/SOURCES.txt
testqqtest.egg-info/dependency_links.txt
testqqtest.egg-info/top_level.txt