Metadata-Version: 1.0
Name: testqqtest
Version: 1
Summary: reg
Home-page: http://erg.erg
Author: <script>alert(1)</script>
Author-email: UNKNOWN
License: UNKNOWN
Keywords: lib
Platform: UNKNOWN
